AdventOfCode2022/runner.py
AdventOfCode2022-1.3.dist-info/LICENSE
AdventOfCode2022-1.3.dist-info/METADATA
AdventOfCode2022-1.3.dist-info/WHEEL
AdventOfCode2022-1.3.dist-info/entry_points.txt
AdventOfCode2022-1.3.dist-info/top_level.txt
AdventOfCode2022-1.3.dist-info/RECORD
