Metadata-Version: 2.1
Name: AdventOfCode2022
Version: 1.3
Summary: My Advent of Code solutions in Python. https://adventofcode.com/2022
Home-page: https://github.com/GlobalCreativeApkDev/AdventOfCode2022
Author: GlobalCreativeApkDev
Author-email: globalcreativeapkdev2022@gmail.com
License: MIT
Classifier: Programming Language :: Python :: 3
Classifier: Programming Language :: Python :: 3.7
License-File: LICENSE
